main.py
ephemeral_terminal_chat-0.1.2.dist-info/METADATA
ephemeral_terminal_chat-0.1.2.dist-info/WHEEL
ephemeral_terminal_chat-0.1.2.dist-info/entry_points.txt
ephemeral_terminal_chat-0.1.2.dist-info/top_level.txt
ephemeral_terminal_chat-0.1.2.dist-info/RECORD
