Metadata-Version: 2.4
Name: ephemeral-terminal-chat
Version: 0.1.2
Summary: Zero-trace terminal chat with 59s read-to-expire logic
Home-page: https://github.com/yourusername/ephemeral-chat
Author: YourName
Requires-Python: >=3.10
Requires-Dist: textual>=0.45.0
Requires-Dist: supabase>=2.3.0
Requires-Dist: python-dotenv>=1.0.0
Requires-Dist: pyperclip>=1.8.2
Dynamic: author
Dynamic: description
Dynamic: description-content-type
Dynamic: home-page
Dynamic: requires-dist
Dynamic: requires-python
Dynamic: summary
